.bumpversion.cfg
.cookiecutterrc
.coveragerc
.editorconfig
AUTHORS.rst
CHANGELOG.rst
CONTRIBUTING.rst
LICENSE
MANIFEST.in
README.rst
setup.cfg
setup.py
tox.ini
ci/bootstrap.py
docs/authors.rst
docs/changelog.rst
docs/conf.py
docs/contributing.rst
docs/index.rst
docs/installation.rst
docs/readme.rst
docs/requirements.txt
docs/spelling_wordlist.txt
docs/usage.rst
docs/reference/client.rst
docs/reference/index.rst
src/jcs_dss_sdk.egg-info/PKG-INFO
src/jcs_dss_sdk.egg-info/SOURCES.txt
src/jcs_dss_sdk.egg-info/dependency_links.txt
src/jcs_dss_sdk.egg-info/not-zip-safe
src/jcs_dss_sdk.egg-info/requires.txt
src/jcs_dss_sdk.egg-info/top_level.txt
src/jcsclient/__init__.py
src/jcsclient/config.py
src/jcsclient/dss_connection.py
src/jcsclient/exception.py
src/jcsclient/filechunkio.py
src/jcsclient/help.py
src/jcsclient/output.py
src/jcsclient/utils.py
src/jcsclient/dss_api/__init__.py
src/jcsclient/dss_api/dss_auth.py
src/jcsclient/dss_api/dss_bucket_ops.py
src/jcsclient/dss_api/dss_object_ops.py
src/jcsclient/dss_api/dss_op.py
src/python_jcsclient.egg-info/PKG-INFO
src/python_jcsclient.egg-info/SOURCES.txt
src/python_jcsclient.egg-info/dependency_links.txt
src/python_jcsclient.egg-info/entry_points.txt
src/python_jcsclient.egg-info/not-zip-safe
src/python_jcsclient.egg-info/requires.txt
src/python_jcsclient.egg-info/top_level.txt